omniblack/repo/__init__.py
omniblack/repo/adventure_schema.json
omniblack/repo/base_package.py
omniblack/repo/cmd_iter.py
omniblack/repo/display.py
omniblack/repo/find_root.py
omniblack/repo/git_branch.py
omniblack/repo/languages.py
omniblack/repo/list_all_files.py
omniblack/repo/metadata_warning.py
omniblack/repo/names.py
omniblack/repo/package_group.py
omniblack/repo/package_info.py
omniblack/repo/sync_metadata.py
omniblack/repo/tree.py
omniblack/repo/version.py
omniblack/repo/yaml.py
omniblack/repo/model/__init__.py
omniblack/repo/model/bugs.json
omniblack/repo/model/build_license.py
omniblack/repo/model/build_target.json
omniblack/repo/model/entry_point.json
omniblack/repo/model/license.json
omniblack/repo/model/license.json.template
omniblack/repo/model/package.json
omniblack/repo/model/package_config.json
omniblack/repo/model/person.json
omniblack/repo/model/unicode.py
omniblack/repo/model/url.py
omniblack/repo/model/version.py
omniblack.repo-0.1.1.dist-info/LICENSE.txt
omniblack.repo-0.1.1.dist-info/METADATA
omniblack.repo-0.1.1.dist-info/WHEEL
omniblack.repo-0.1.1.dist-info/entry_points.txt
omniblack.repo-0.1.1.dist-info/top_level.txt
omniblack.repo-0.1.1.dist-info/RECORD
