Metadata-Version: 2.1
Name: omniblack.repo
Version: 0.1.1
Summary: Tooling for interacting with monorepos.
Author-email: Terry Patterson <Terryp@wegrok.net>
License: 
Project-URL: Homepage, https://gitlab.com/terryp/terry/-/tree/next/tooling/repo
Project-URL: Repository, https://gitlab.com/terryp/terry.git
Classifier: Intended Audience :: Developers
Classifier: Programming Language :: Python :: 3 :: Only
Classifier: Topic :: Software Development
Requires-Python: ~=3.9
License-File: LICENSE.txt
Requires-Dist: atpublic ~=4.0
Requires-Dist: omniblack.model
Requires-Dist: omniblack.repo
Requires-Dist: packaging
Requires-Dist: pydantic[email]
Requires-Dist: requests
Requires-Dist: rich
Requires-Dist: ruamel.yaml ~=0.18
Requires-Dist: sh ~=2.0
Requires-Dist: tomlkit ~=0.7
Requires-Dist: fs ~=2.4
